<?xml version="1.0" encoding="utf-8" ?><dwsync><file name="01.html" server="carlislemencap.co.uk//public_html/" local="3332240978" remote="11959323992" /><file name="02.html" server="carlislemencap.co.uk//public_html/" local="3332240985" remote="11959323992" /><file name="03.html" server="carlislemencap.co.uk//public_html/" local="3332240993" remote="11959323992" /><file name=".DS_Store" server="numyspace.co.uk/public_html/" local="3377531831" remote="11967467280" /><file name="01.html" server="numyspace.co.uk/public_html/" local="3332240978" remote="11967469075" /><file name="02.html" server="numyspace.co.uk/public_html/" local="3332240985" remote="11967469076" /><file name="03.html" server="numyspace.co.uk/public_html/" local="3332240993" remote="11967469076" /><file name="01.html" server="92.48.78.239//public_html/" local="3332240978" remote="12003263972" /><file name="02.html" server="92.48.78.239//public_html/" local="3332240985" remote="12003263972" /><file name="03.html" server="92.48.78.239//public_html/" local="3332240993" remote="12003263972" /></dwsync>